{
  "quizlist": [
    {
      "question": "¿Cuántos Pokémon hay en la región Kanto?",
      "options": [
        "150",
        "200",
        "151",
        "99"
      ],
      "correcta": "2"
    },
    {
      "question": "¿Contra qué tipos es fuerte el tipo Eléctrico?",
      "options": [
        "Siniestro - Psíquico",
        "Planta",
        "Acero",
        "Agua - Volador"
      ],
      "correcta": "3"
    },
    {
      "question": "¿Cómo se llama la evolución tipo hada de Eevee?",
      "options": [
        "Glaceon",
        "Leafeon",
        "Sylveon",
        "Gliscor"
      ],
      "correcta": "2"
    },
    {
      "question": "¿De qué tipo es Sceptile cuando megaevoluciona?",
      "options": [
        "Planta - Acero",
        "Planta",
        "Agua",
        "Planta - Dragón"
      ],
      "correcta": "3"
    },
    {
      "question": "¿En cuál generación se introdujo la megavolución?",
      "options": [
        "VI",
        "IV",
        "II",
        "VIII"
      ],
      "correcta": "0"
    }
  ]
}